tweepypoll/__init__.py
tweepypoll/tweepypoll.py
tweepypoll-0.3.0.dist-info/LICENSE
tweepypoll-0.3.0.dist-info/WHEEL
tweepypoll-0.3.0.dist-info/METADATA
tweepypoll-0.3.0.dist-info/RECORD
