Metadata-Version: 2.1
Name: tweepypoll
Version: 0.3.0
Summary: Collect and visualize twitter poll data.
Home-page: https://github.com/UBC-MDS/tweepypoll
License: MIT
Author: Wenxin Xiang, Rada Rudyak, Linh Giang Nguyen
Requires-Python: >=3.9,<4.0
Classifier: License :: OSI Approved :: MIT License
Classifier: Programming Language :: Python :: 3
Classifier: Programming Language :: Python :: 3.10
Classifier: Programming Language :: Python :: 3.9
Requires-Dist: Sphinx (>=4.4.0,<5.0.0)
Requires-Dist: altair (>=4.2.0,<5.0.0)
Requires-Dist: pandas (>=1.3.5,<2.0.0)
Requires-Dist: python-dotenv (>=0.19.2,<0.20.0)
Requires-Dist: tweepy (>=4.4.0,<5.0.0)
Project-URL: Documentation, https://tweepypoll.readthedocs.io
Project-URL: Repository, https://github.com/UBC-MDS/tweepypoll
